pydaves/__init__.py
pydaves/utils.py
pydaves/torchsystem/__init__.py
pydaves/torchsystem/torchloaders.py
pydaves/torchsystem/torchmodels.py
pydaves/torchsystem/torchsystem.py
pydaves/torchsystem/torchutils.py
pydaves-1.1.6.dist-info/LICENSE
pydaves-1.1.6.dist-info/METADATA
pydaves-1.1.6.dist-info/WHEEL
pydaves-1.1.6.dist-info/top_level.txt
pydaves-1.1.6.dist-info/RECORD
