Metadata-Version: 2.1
Name: pydaves
Version: 1.1.6
Summary: Personal utils package for my Python projects
Home-page: https://github.com/davidemiani/pydaves
Author: Davide Miani
Author-email: davide.miani2@gmail.com
License: UNKNOWN
Platform: UNKNOWN
Classifier: Programming Language :: Python :: 3
Classifier: License :: OSI Approved :: MIT License
Classifier: Operating System :: OS Independent
Requires-Python: >=3.6
